vectorizer_ai/__init__.py
vectorizer_ai/client.py
vectorizer_ai/utils.py
vectorizer_ai-2.0.2.dist-info/METADATA
vectorizer_ai-2.0.2.dist-info/WHEEL
vectorizer_ai-2.0.2.dist-info/top_level.txt
vectorizer_ai-2.0.2.dist-info/RECORD
