Metadata-Version: 2.1
Name: vectorizer-ai
Version: 2.0.2
Summary: Python SDK for vectorizer.ai
Home-page: https://github.com/mitchbregs/vectorizer-ai
Author: Mitchell Bregman
Author-email: mitch@mitchbregs.com
Keywords: vectorizer.ai svg vectorize image
Classifier: Development Status :: 3 - Alpha
Classifier: Intended Audience :: Developers
Classifier: Programming Language :: Python :: 3
Requires-Python: >3.6
Requires-Dist: requests
